{
    "Life & Health Insurance": [
        "AFL", 
        "MET", 
        "PFG", 
        "PRU"
    ], 
    "Home Improvement Retail": [
        "HD"
    ], 
    "Food Retail": [
        "KR"
    ], 
    "Health Care Services": [
        "DGX"
    ], 
    "Industrial Machinery": [
        "PNR", 
        "CMI", 
        "FLS", 
        "IR", 
        "ITW", 
        "PH", 
        "DOV"
    ], 
    "Environmental & Facilities Services": [
        "RSG"
    ], 
    "Apparel, Accessories & Luxury Goods": [
        "RL", 
        "COH", 
        "NKE", 
        "PVH"
    ], 
    "Oil & Gas Refining & Marketing": [
        "MPC"
    ], 
    "Electronic Components": [
        "APH", 
        "GLW"
    ], 
    "Computer & Electronics Retail": [
        "BBY"
    ], 
    "Investment Banking & Brokerage": [
        "RJF", 
        "GS", 
        "MS", 
        "SCHW"
    ], 
    "Multi-Utilities": [
        "NI", 
        "EXC", 
        "CNP", 
        "SRE", 
        "SCG", 
        "NEE", 
        "DTE", 
        "AEE", 
        "PNW", 
        "CMS", 
        "ES"
    ], 
    "Office REITs": [
        "BXP", 
        "SLG"
    ], 
    "Aerospace & Defense": [
        "BA", 
        "RTN", 
        "LMT", 
        "NOC", 
        "GD", 
        "LLL", 
        "COL"
    ], 
    "Construction Materials": [
        "MLM"
    ], 
    "Restaurants": [
        "DRI", 
        "SBUX"
    ], 
    "Automotive Retail": [
        "AAP"
    ], 
    "Automobile Manufacturers": [
        "F"
    ], 
    "Semiconductors": [
        "MCHP", 
        "NVDA", 
        "INTC", 
        "ADI"
    ], 
    "Health Care Equipment": [
        "A", 
        "MDT", 
        "ABT", 
        "BCR", 
        "BAX"
    ], 
    "Department Stores": [
        "M", 
        "JWN"
    ], 
    "Drug Retail": [
        "CVS"
    ], 
    "Research & Consulting Services": [
        "EFX"
    ], 
    "Regional Banks": [
        "PNC", 
        "BBT", 
        "RF", 
        "KEY", 
        "HBAN"
    ], 
    "Agricultural Products": [
        "ADM"
    ], 
    "Housewares & Specialties": [
        "NWL"
    ], 
    "IT Consulting & Other Services": [
        "ACN", 
        "IBM"
    ], 
    "Diversified Support Services": [
        "CTAS"
    ], 
    "Industrial Conglomerates": [
        "HON", 
        "MMM", 
        "GE", 
        "ROP"
    ], 
    "Household Appliances": [
        "SNA"
    ], 
    "Multi-line Insurance": [
        "L", 
        "LNC", 
        "AIZ"
    ], 
    "Industrial Materials": [
        "GWW"
    ], 
    "Integrated Telecommunication Services": [
        "CTL"
    ], 
    "Specialized REITs": [
        "DLR", 
        "PSA", 
        "EXR", 
        "AMT", 
        "IRM"
    ], 
    "Data Processing & Outsourced Services": [
        "GPN"
    ], 
    "Diversified Chemicals": [
        "EMN"
    ], 
    "Construction Machinery & Heavy Trucks": [
        "PCAR"
    ], 
    "Home Furnishings": [
        "LEG"
    ], 
    "Residential REITs": [
        "MAA", 
        "EQR", 
        "ESS", 
        "AVB"
    ], 
    "Insurance Brokers": [
        "AON", 
        "MMC", 
        "AJG"
    ], 
    "Packaged Foods & Meats": [
        "GIS", 
        "HRL", 
        "CPB", 
        "MDLZ", 
        "SJM", 
        "MKC", 
        "HSY", 
        "CAG"
    ], 
    "Asset Management & Custody Banks": [
        "AMP", 
        "BEN", 
        "IVZ", 
        "BLK", 
        "NTRS"
    ], 
    "Railroads": [
        "KSU", 
        "NSC", 
        "CSX"
    ], 
    "Hotels, Resorts & Cruise Lines": [
        "RCL", 
        "CCL", 
        "MAR"
    ], 
    "Internet & Direct Marketing Retail": [
        "EXPE"
    ], 
    "Systems Software": [
        "CA"
    ], 
    "Apparel Retail": [
        "ROST", 
        "FL", 
        "GPS"
    ], 
    "Cable & Satellite": [
        "SNI"
    ], 
    "Fertilizers & Agricultural Chemicals": [
        "MOS", 
        "FMC"
    ], 
    "Specialty Chemicals": [
        "PPG", 
        "SHW", 
        "ECL", 
        "ALB", 
        "IFF", 
        "LYB"
    ], 
    "Diversified Banks": [
        "C", 
        "JPM", 
        "BAC", 
        "CMA"
    ], 
    "Personal Products": [
        "EL", 
        "PG"
    ], 
    "Pharmaceuticals": [
        "LLY", 
        "PFE"
    ], 
    "Building Products": [
        "FAST"
    ], 
    "Water Utilities": [
        "AWK"
    ], 
    "Homebuilding": [
        "LEN", 
        "DHI"
    ], 
    "Consumer Electronics": [
        "GRMN"
    ], 
    "Household Products": [
        "CLX", 
        "CHD"
    ], 
    "Human Resource & Employment Services": [
        "RHI"
    ], 
    "Retail REITs": [
        "GGP", 
        "O", 
        "MAC", 
        "KIM", 
        "FRT", 
        "REG", 
        "SPG"
    ], 
    "Electronic Equipment & Instruments": [
        "FLIR"
    ], 
    "Steel": [
        "NUE"
    ], 
    "Electrical Components & Equipment": [
        "AYI", 
        "ROK", 
        "AME", 
        "ETN"
    ], 
    "Tobacco": [
        "MO", 
        "RAI"
    ], 
    "Semiconductor Equipment": [
        "AMAT", 
        "KLAC"
    ], 
    "Trucking": [
        "R", 
        "JBHT"
    ], 
    "Broadcasting": [
        "CBS"
    ], 
    "Internet Software & Services": [
        "INTU", 
        "FIS", 
        "PAYX", 
        "MA", 
        "ADP"
    ], 
    "Industrial REITs": [
        "PLD"
    ], 
    "Multi-Sector Holdings": [
        "LUK"
    ], 
    "Specialty Stores": [
        "SIG", 
        "GPC"
    ], 
    "Managed Health Care": [
        "ANTM", 
        "HUM", 
        "AET"
    ], 
    "Paper Packaging": [
        "IP", 
        "SEE", 
        "AVY"
    ], 
    "Publishing": [
        "FOXA", 
        "FOX"
    ], 
    "General Merchandise Stores": [
        "KSS"
    ], 
    "Airlines": [
        "LUV"
    ], 
    "Oil & Gas Storage & Transportation": [
        "OKE", 
        "KMI"
    ], 
    "Air Freight & Logistics": [
        "CHRW", 
        "FDX", 
        "EXPD"
    ], 
    "Soft Drinks": [
        "KO", 
        "DPS", 
        "PEP"
    ], 
    "Communications Equipment": [
        "CSCO", 
        "HRS"
    ], 
    "Property & Casualty Insurance": [
        "CINF", 
        "CB", 
        "ALL", 
        "PGR"
    ], 
    "Health Care REITs": [
        "HCP", 
        "HCN"
    ], 
    "Advertising": [
        "OMC", 
        "IPG"
    ], 
    "Metal & Glass Containers": [
        "BLL"
    ], 
    "Biotechnology": [
        "AMGN"
    ], 
    "Health Care Supplies": [
        "PDCO"
    ], 
    "Home Entertainment Software": [
        "ATVI"
    ], 
    "Industrial Gases": [
        "PX", 
        "APD"
    ], 
    "Application Software": [
        "ORCL"
    ], 
    "Consumer Finance": [
        "AXP", 
        "DFS", 
        "COF"
    ], 
    "Health Care Distributors": [
        "MCK", 
        "BMY", 
        "CAH"
    ], 
    "Motorcycle Manufacturers": [
        "HOG"
    ], 
    "Construction & Engineering": [
        "FLR"
    ], 
    "Leisure Products": [
        "HAS", 
        "MAT"
    ], 
    "Financial Exchanges & Data": [
        "SPGI", 
        "CME", 
        "CBOE", 
        "NDAQ"
    ], 
    "Electric Utilities": [
        "AEP", 
        "DUK", 
        "D", 
        "EIX", 
        "ED", 
        "PPL", 
        "SO", 
        "LNT"
    ]
}